Dbias/__init__.py
Dbias/bias_classification.py
Dbias/bias_masking.py
Dbias/bias_recognition.py
Dbias/text_debiasing.py
Dbias-0.1.5.dist-info/METADATA
Dbias-0.1.5.dist-info/WHEEL
Dbias-0.1.5.dist-info/top_level.txt
Dbias-0.1.5.dist-info/RECORD
